Metadata-Version: 2.1
Name: gmailnator.py
Version: 1.0.2
Summary: Python wrapper to access Gmailnator programmatically
Home-page: https://github.com/L3afMe/Gmailnator.py
Author: L3afMe
Author-email: L3afMeAlon3@gmail.com
License: GNU GPLv3 or later
Platform: UNKNOWN
